image_processing/__init__.py
image_processing/processing/__init__.py
image_processing/processing/combination.py
image_processing/processing/transformation.py
image_processing/utils/__init__.py
image_processing/utils/io.py
image_processing/utils/plot.py
image_processing_vitor_valim/__init__.py
image_processing_vitor_valim/processing/__init__.py
image_processing_vitor_valim/processing/combination.py
image_processing_vitor_valim/processing/transformation.py
image_processing_vitor_valim/utils/__init__.py
image_processing_vitor_valim/utils/io.py
image_processing_vitor_valim/utils/plot.py
image_processing_vitor_valim_fix/__init__.py
image_processing_vitor_valim_fix/processing/__init__.py
image_processing_vitor_valim_fix/processing/combination.py
image_processing_vitor_valim_fix/processing/transformation.py
image_processing_vitor_valim_fix/utils/__init__.py
image_processing_vitor_valim_fix/utils/io.py
image_processing_vitor_valim_fix/utils/plot.py
image_processing_vitor_valim_fix-0.1.1.dist-info/METADATA
image_processing_vitor_valim_fix-0.1.1.dist-info/WHEEL
image_processing_vitor_valim_fix-0.1.1.dist-info/top_level.txt
image_processing_vitor_valim_fix-0.1.1.dist-info/RECORD
