Metadata-Version: 2.4
Name: image_processing_vitor_valim_fix
Version: 0.1.1
Summary: Transformador de tonalidade em imagens
Home-page: https://github.com/vitorvalim/image-package
Author: Vitor Gomes Valim
Author-email: vitorvalim1@hotmail.com
Requires-Python: >=3.8
Requires-Dist: matplotlib
Requires-Dist: numpy
Requires-Dist: scikit-image>=0.16.1
Requires-Dist: opencv-python
Dynamic: author
Dynamic: author-email
Dynamic: description
Dynamic: description-content-type
Dynamic: home-page
Dynamic: requires-dist
Dynamic: requires-python
Dynamic: summary
